{"stat.walkOneCm":315363,"stat.useItem.minecraft.structure_void":37,"stat.trappedChestTriggered":5,"stat.useItem.minecraft.stone":25,"stat.leaveGame":4,"stat.jump":6491,"stat.swimOneCm":19807,"stat.fallOneCm":62781,"stat.shulkerBoxOpened":34,"stat.crouchOneCm":13471,"stat.useItem.minecraft.stained_hardened_clay":3,"stat.pickup.minecraft.sticky_piston":10,"stat.sprintOneCm":471045,"stat.useItem.minecraft.stained_glass":3,"stat.useItem.minecraft.concrete":2,"stat.pickup.minecraft.repeater":4,"stat.damageTaken":2025,"stat.flyOneCm":1646707,"stat.pickup.minecraft.lever":1,"stat.deaths":4,"stat.playOneMinute":174843,"stat.pickup.minecraft.stone_button":4,"stat.entityKilledBy.Zombie":1,"stat.sneakTime":6352,"stat.entityKilledBy.Blaze":1,"stat.useItem.minecraft.wool":100,"stat.timeSinceDeath":2488,"stat.diveOneCm":8395,"stat.useItem.minecraft.iron_door":1}